betfair_parser/__init__.py
betfair_parser/cache.py
betfair_parser/client.py
betfair_parser/endpoints.py
betfair_parser/exceptions.py
betfair_parser/spec/__init__.py
betfair_parser/spec/accounts/__init__.py
betfair_parser/spec/accounts/enums.py
betfair_parser/spec/accounts/operations.py
betfair_parser/spec/accounts/type_definitions.py
betfair_parser/spec/betting/__init__.py
betfair_parser/spec/betting/enums.py
betfair_parser/spec/betting/listings.py
betfair_parser/spec/betting/operations.py
betfair_parser/spec/betting/orders.py
betfair_parser/spec/betting/type_definitions.py
betfair_parser/spec/common/__init__.py
betfair_parser/spec/common/enums.py
betfair_parser/spec/common/messages.py
betfair_parser/spec/common/type_definitions.py
betfair_parser/spec/heartbeat.py
betfair_parser/spec/identity.py
betfair_parser/spec/navigation.py
betfair_parser/spec/race_status.py
betfair_parser/spec/streaming/__init__.py
betfair_parser/spec/streaming/enums.py
betfair_parser/spec/streaming/messages.py
betfair_parser/spec/streaming/type_definitions.py
betfair_parser/stream.py
betfair_parser/strenums.py
betfair_parser-0.17.4.dist-info/METADATA
betfair_parser-0.17.4.dist-info/WHEEL
betfair_parser-0.17.4.dist-info/licenses/LICENSE.txt
betfair_parser-0.17.4.dist-info/RECORD
