Metadata-Version: 2.4
Name: betfair_parser
Version: 0.17.4
Summary: A betfair parser
License: Copyright 2023, betfair_parser developers
License-File: LICENSE.txt
Keywords: parser,betfair,api,json,streaming
Author: Bradley McElroy
Author-email: bradley.mcelroy@live.com
Requires-Python: >=3.10
Classifier: Programming Language :: Python :: 3
Classifier: Programming Language :: Python :: 3.10
Classifier: Programming Language :: Python :: 3.11
Classifier: Programming Language :: Python :: 3.12
Classifier: Programming Language :: Python :: 3.13
Classifier: License :: OSI Approved :: BSD License
Classifier: Operating System :: OS Independent
Classifier: Topic :: Software Development :: Libraries
Classifier: Topic :: File Formats :: JSON
Classifier: Development Status :: 4 - Beta
Provides-Extra: dev
Requires-Dist: msgspec (>=0.19.0)
Requires-Dist: pytest (>=7.1) ; extra == "dev"
Requires-Dist: pytest-asyncio (>=0.21.0) ; extra == "dev"
Requires-Dist: pytest-benchmark (>=4.0) ; extra == "dev"
Requires-Dist: requests (>=2.20.0) ; extra == "dev"
Requires-Dist: twine (>=4.0.2) ; extra == "dev"
Project-URL: Bug Tracker, https://github.com/limx0/betfair_parser/issues
Project-URL: Documentation, https://limx0.github.io/betfair_parser/
Project-URL: Homepage, https://github.com/limx0/betfair_parser
